countfiles/__init__.py
countfiles/__main__.py
countfiles/core.py
countfiles/countfiles.py
countfiles/data.py
src/Countfiles.py
src/__init__.py
src/__main__.py
countfiles-0.3.4.dist-info/LICENSE
countfiles-0.3.4.dist-info/METADATA
countfiles-0.3.4.dist-info/WHEEL
countfiles-0.3.4.dist-info/top_level.txt
countfiles-0.3.4.dist-info/RECORD
