Metadata-Version: 2.1
Name: countfiles
Version: 0.3.4
Summary: A simple module to count or list the attributes of files in a directory.
Home-page: https://github.com/pypa/sampleproject
Author: Aiden Blishen Cuneo
Author-email: aidencuneo@gmail.com
License: UNKNOWN
Platform: UNKNOWN
Classifier: Programming Language :: Python :: 3
Classifier: License :: OSI Approved :: MIT License
Classifier: Operating System :: OS Independent
Requires-Python: >=3.1
